{
  "entries": [
    {
      "key": "SOFT_DESC",
      "value": "?????"
    },
    {
      "key": "HOT_DESC",
      "value": "?????"
    },
    {
      "key": "HARD_DESC",
      "value": "?????"
    },
    {
      "key": "EXTREAM_DESC",
      "value": "??????????"
    },
    {
      "key": "CONFIRM_EXIT",
      "value": "??? ???????"
    },
    {
      "key": "text_key",
      "value": "??"
    },
    {
      "key": "DRINK_0001",
      "value": "????????????????????2"
    },
    {
      "key": "DRINK_0002",
      "value": "??????????????????????2"
    },
    {
      "key": "DRINK_0003",
      "value": "????????????????????????????????3"
    },
    {
      "key": "DRINK_0004",
      "value": "???????????????????1"
    },
    {
      "key": "DRINK_0005",
      "value": "???????????????????????1"
    },
    {
      "key": "DRINK_0006",
      "value": "?????????????????????????1"
    },
    {
      "key": "DRINK_0007",
      "value": "?????????????????????????????????1"
    },
    {
      "key": "DRINK_0008",
      "value": "????????????????????????????????????1"
    },
    {
      "key": "DRINK_0009",
      "value": "??????????????????????????1"
    },
    {
      "key": "DRINK_0010",
      "value": "????????????????????????????????1"
    },
    {
      "key": "DRINK_0011",
      "value": "??????????????????????????1"
    },
    {
      "key": "DRINK_0012",
      "value": "???????????????????2"
    },
    {
      "key": "DRINK_0013",
      "value": "????????????????????????????????1"
    },
    {
      "key": "DRINK_0014",
      "value": "?????????????????????????3"
    },
    {
      "key": "DRINK_0015",
      "value": "??????????????????????1"
    },
    {
      "key": "DRINK_0016",
      "value": "???4??4"
    },
    {
      "key": "DRINK_0017",
      "value": "??????????????????????????4"
    },
    {
      "key": "DRINK_0018",
      "value": "?????????????????????????????????????4"
    },
    {
      "key": "DRINK_0019",
      "value": "??????????????????????????????1"
    },
    {
      "key": "DRINK_0020",
      "value": "?????????????????????????3"
    }
  ]
}